teritorio/__init__.py
teritorio/__version__.py
teritorio/_data/country.json
teritorio/_data/currency.json
teritorio/main.py
teritorio/main.pyi
teritorio/py.typed
teritorio-2025.11.11.dist-info/LICENSE.md
teritorio-2025.11.11.dist-info/METADATA
teritorio-2025.11.11.dist-info/WHEEL
teritorio-2025.11.11.dist-info/RECORD
