Metadata-Version: 2.3
Name: teritorio
Version: 2025.11.11
Summary: A library for country and currency ISO codes
Home-page: https://teritorio.readthedocs.io/en/stable/
License: BSD-3-Clause
Keywords: country,currency,iso
Author: Stephanos Kuma
Author-email: "Stephanos Kuma" <stephanos@kuma.ai>
Requires-Python: >=3.10
Classifier: Development Status :: 5 - Production/Stable
Classifier: Intended Audience :: Financial and Insurance Industry
Classifier: License :: OSI Approved :: BSD License
Classifier: Operating System :: OS Independent
Classifier: Programming Language :: Python :: 3 :: Only
Requires-Dist: pyutilkit (~=0.11)
Project-URL: Documentation, https://teritorio.readthedocs.io/en/stable/
Project-URL: Repository, https://github.com/spapanik/teritorio
